Hello33423312/__init__.py
Hello33423312/hello.py
Hello33423312-0.1.dist-info/LICENSE
Hello33423312-0.1.dist-info/METADATA
Hello33423312-0.1.dist-info/WHEEL
Hello33423312-0.1.dist-info/top_level.txt
Hello33423312-0.1.dist-info/RECORD
