Metadata-Version: 2.1
Name: Hello33423312
Version: 0.1
Summary: Clear untuk Kode Kelompok
Home-page: https://github.com/syahrulcaem/Informasi_negara
Author: scaem007
Author-email: <syahrulromadhonmuhamamd@gmail.com>
License: MIT
Keywords: Hello
Classifier: Development Status :: 1 - Planning
License-File: LICENSE
